splitmasked/__init__.py
splitmasked/io.py
splitmasked/split.py
splitmasked-0.1.1.dist-info/LICENSE
splitmasked-0.1.1.dist-info/METADATA
splitmasked-0.1.1.dist-info/WHEEL
splitmasked-0.1.1.dist-info/entry_points.txt
splitmasked-0.1.1.dist-info/top_level.txt
splitmasked-0.1.1.dist-info/RECORD
