Metadata-Version: 2.1
Name: splitmasked
Version: 0.1.1
Summary: Separate masked and unmasked parts of sequences in FASTX files.
Home-page: https://github.com/osthomas/splitmasked
Project-URL: Bug Tracker, https://github.com/osthomas/splitmasked/issues
Classifier: Programming Language :: Python :: 3
Classifier: Operating System :: OS Independent
Requires-Python: >=3.0
License-File: LICENSE
Requires-Dist: streamseqs (>=0.1.0)
